themizer/.vscode/settings.json
themizer/__init__.py
themizer/args.py
themizer/config.py
themizer/controller.py
themizer/exceptions.py
themizer/messages.py
themizer/theme_model.py
themizer/themes_manager.py
themizer-1.1.2.dist-info/entry_points.txt
themizer-1.1.2.dist-info/WHEEL
themizer-1.1.2.dist-info/METADATA
themizer-1.1.2.dist-info/RECORD
