Metadata-Version: 2.1
Name: themizer
Version: 1.1.2
Summary: An easy and fast CLI app to change between custom themes in Unix-like systems.
Home-page: https://github.com/kutu-dev/themizer
License: MIT
Keywords: themes,utility,manager
Author: kutu-dev
Requires-Python: >=3.11,<4.0
Classifier: Development Status :: 5 - Production/Stable
Classifier: License :: OSI Approved :: MIT License
Classifier: Operating System :: OS Independent
Classifier: Programming Language :: Python :: 3
Classifier: Programming Language :: Python :: 3.11
Classifier: Topic :: Utilities
Requires-Dist: colorama (>=0.4.6,<0.5.0)
Project-URL: Repository, https://github.com/kutu-dev/themizer
